tadl/__init__.py
tadl/descriptor.py
tadl/match.py
tadl/py.typed
tadl/query.py
tadl/query_batch.py
tadl/query_group.py
tadl/query_interface.py
tadl/types.py
tadl-0.1.2.dist-info/METADATA
tadl-0.1.2.dist-info/WHEEL
tadl-0.1.2.dist-info/RECORD
