Metadata-Version: 2.1
Name: tadl
Version: 0.1.2
Summary: 
Author: Travis DePrato
Author-email: hey@twavv.me
Requires-Python: >=3.11,<4.0
Classifier: Programming Language :: Python :: 3
Classifier: Programming Language :: Python :: 3.11
Classifier: Programming Language :: Python :: 3.12
Requires-Dist: strawberry-graphql (>=0.227.2,<0.228.0)
